get_holiday_cn/__init__.py
get_holiday_cn/client.py
get_holiday_cn-1.0.7.dist-info/LICENSE
get_holiday_cn-1.0.7.dist-info/METADATA
get_holiday_cn-1.0.7.dist-info/WHEEL
get_holiday_cn-1.0.7.dist-info/top_level.txt
get_holiday_cn-1.0.7.dist-info/RECORD
