Metadata-Version: 2.1
Name: get_holiday_cn
Version: 1.0.7
Summary: 获取中国法定节假日
Home-page: https://github.com/longweiqiang/get_holiday_cn
Author: Weiqiang.long
Classifier: Programming Language :: Python :: 3
Classifier: License :: OSI Approved :: MIT License
Classifier: Operating System :: OS Independent
License-File: LICENSE
